{
  "appName": "qa-dashboard",
  "version": "1.0.0",
  "displayVersion": "1.0.0.2606031121",
  "buildNumber": 2606031121,
  "releaseLabel": "v1.0.0.2606031121",
  "updatedAt": "03/06/2026 11:21:51",
  "timezone": "Asia/Bangkok",
  "author": "Songpon Phothong",
  "commitHash": "f574f829486ba8e1c579d642ae2c6661b12e7983",
  "commitMessage": "Persist submitted evaluation deletes",
  "changedFiles": [
    "public/build-meta.json",
    "src/CreateEvaluationMockup.tsx",
    "src/evaluationStore.ts"
  ],
  "releaseNotesTitle": "Latest Updates",
  "releaseNotes": []
}