{
  "appName": "qa-dashboard",
  "version": "1.0.0",
  "displayVersion": "1.0.0.2605152027",
  "buildNumber": 2605152027,
  "releaseLabel": "v1.0.0.2605152027",
  "updatedAt": "15/05/2026 20:27:38",
  "timezone": "Asia/Bangkok",
  "author": "Songpon Phothong",
  "commitHash": "8f0e64e583c7fbea86f715c1883f487ee43104a3",
  "commitMessage": "Clear create evaluation defaults",
  "changedFiles": [
    "public/build-meta.json",
    "src/CreateEvaluationMockup.tsx"
  ],
  "releaseNotesTitle": "Latest Updates",
  "releaseNotes": []
}