{
  "appName": "qa-dashboard",
  "version": "1.0.0",
  "displayVersion": "1.0.0.2605141551",
  "buildNumber": 2605141551,
  "releaseLabel": "v1.0.0.2605141551",
  "updatedAt": "14/05/2026 15:51:52",
  "timezone": "Asia/Bangkok",
  "author": "Songpon Phothong",
  "commitHash": "26536cc5ea86fb3a8330fadbd93777f750a6220e",
  "commitMessage": "Clarify role management controls",
  "changedFiles": [
    "public/build-meta.json",
    "src/UserRoleAdminMockup.tsx"
  ],
  "releaseNotesTitle": "Latest Updates",
  "releaseNotes": []
}